<?xml version="1.0" encoding="utf-8" ?>
<dwsync>
<file name="application.xml" server="ftp.ipx-lab.com" local="130690950000000000" remote="130690950000000000" />
<file name="booking.xml" server="ftp.ipx-lab.com" local="130690950000000000" remote="130690950000000000" />
<file name="catalog.xml" server="ftp.ipx-lab.com" local="130690950000000000" remote="130690950000000000" />
<file name="cms.xml" server="ftp.ipx-lab.com" local="130690950000000000" remote="130690950000000000" />
<file name="comment.xml" server="ftp.ipx-lab.com" local="130690950000000000" remote="130690950000000000" />
<file name="contact.xml" server="ftp.ipx-lab.com" local="130690950000000000" remote="130690950000000000" />
<file name="customer.xml" server="ftp.ipx-lab.com" local="130690950000000000" remote="130690950000000000" />
<file name="event.xml" server="ftp.ipx-lab.com" local="130690950000000000" remote="130690950000000000" />
<file name="folder.xml" server="ftp.ipx-lab.com" local="130690950000000000" remote="130690950000000000" />
<file name="form.xml" server="ftp.ipx-lab.com" local="130690950000000000" remote="130690950000000000" />
<file name="front.xml" server="ftp.ipx-lab.com" local="130690950000000000" remote="130690950000000000" />
<file name="home.xml" server="ftp.ipx-lab.com" local="130690950000000000" remote="130690950000000000" />
<file name="loyaltycard.xml" server="ftp.ipx-lab.com" local="130690950000000000" remote="130690950000000000" />
<file name="map.xml" server="ftp.ipx-lab.com" local="130690950000000000" remote="130690950000000000" />
<file name="media.xml" server="ftp.ipx-lab.com" local="130690950000000000" remote="130690950000000000" />
<file name="padlock.xml" server="ftp.ipx-lab.com" local="130690950000000000" remote="130690950000000000" />
<file name="promotion.xml" server="ftp.ipx-lab.com" local="130690950000000000" remote="130690950000000000" />
<file name="push.xml" server="ftp.ipx-lab.com" local="130690950000000000" remote="130690950000000000" />
<file name="rss.xml" server="ftp.ipx-lab.com" local="130690950000000000" remote="130690950000000000" />
<file name="social.xml" server="ftp.ipx-lab.com" local="130690950000000000" remote="130690950000000000" />
<file name="socialgaming.xml" server="ftp.ipx-lab.com" local="130690950000000000" remote="130690950000000000" />
<file name="weblink.xml" server="ftp.ipx-lab.com" local="130690950000000000" remote="130690950000000000" />
<file name="wordpress.xml" server="ftp.ipx-lab.com" local="130690950000000000" remote="130690950000000000" />
</dwsync>